Metadata-Version: 2.1
Name: BigBookPython
Version: 0.1.1
Summary: A module to install the dependencies for the projects in The Big Book of Small Python Projects.
Home-page: https://github.com/asweigart/bigbookpython
Author: Al Sweigart
Author-email: al@inventwithpython.com
License: MIT
Platform: UNKNOWN
Classifier: License :: OSI Approved :: MIT License
Classifier: Programming Language :: Python
Classifier: Programming Language :: Python :: 3
Classifier: Programming Language :: Python :: 3.5
Classifier: Programming Language :: Python :: 3.6
Classifier: Programming Language :: Python :: 3.7
Classifier: Programming Language :: Python :: 3.8
Classifier: Programming Language :: Python :: 3.9
